plmbench/__init__.py
plmbench/__main__.py
plmbench/app.py
plmbench/py.typed
plmbench/samples.py
plmbench/topics/__init__.py
plmbench/topics/assembly/__init__.py
plmbench/topics/assembly/app.py
plmbench/topics/assembly/description.py
plmbench/topics/assembly/gfa_connector/__init__.py
plmbench/topics/assembly/gfa_connector/description.py
plmbench/topics/assembly/results.py
plmbench/topics/assembly/skesa/__init__.py
plmbench/topics/assembly/skesa/description.py
plmbench/topics/assembly/unicycler/__init__.py
plmbench/topics/assembly/unicycler/app.py
plmbench/topics/assembly/unicycler/bash.py
plmbench/topics/assembly/unicycler/connector.py
plmbench/topics/assembly/unicycler/core_command.sh
plmbench/topics/assembly/unicycler/description.py
plmbench/topics/assembly/visitor.py
plmbench/topics/binning/__init__.py
plmbench/topics/binning/app.py
plmbench/topics/binning/description.py
plmbench/topics/binning/pangebin_once/__init__.py
plmbench/topics/binning/pangebin_once/app.py
plmbench/topics/binning/pangebin_once/connector.py
plmbench/topics/binning/pangebin_once/core_command.sh
plmbench/topics/binning/pangebin_once/description.py
plmbench/topics/binning/pangebin_once/init.py
plmbench/topics/binning/pangebin_once/shell.py
plmbench/topics/binning/plasbin_flow/format/__init__.py
plmbench/topics/binning/plasbin_flow/format/classification/__init__.py
plmbench/topics/binning/plasbin_flow/format/classification/ops.py
plmbench/topics/binning/plasbin_flow/format/classification/plasgraph2.py
plmbench/topics/binning/plasbin_flow/format/classification/platon.py
plmbench/topics/binning/plasbin_flow/format/classification/results.py
plmbench/topics/binning/plasbin_flow/format/classification/visitor.py
plmbench/topics/binning/visitor.py
plmbench/topics/classification/__init__.py
plmbench/topics/classification/app.py
plmbench/topics/classification/description.py
plmbench/topics/classification/plasclass/__init__.py
plmbench/topics/classification/plasclass/app.py
plasmid_bin_bench-0.0.10.dist-info/WHEEL
plasmid_bin_bench-0.0.10.dist-info/entry_points.txt
plasmid_bin_bench-0.0.10.dist-info/METADATA
plasmid_bin_bench-0.0.10.dist-info/RECORD
