Metadata-Version: 2.3
Name: plasmid-bin-bench
Version: 0.0.10
Summary: Plasmid binning benchmark.
Author: vepain, acme92
Author-email: vepain <victorepain@disroot.org>, acme92 <amane@sfu.ca>
License: # GNU GENERAL PUBLIC LICENSE
Requires-Dist: biopython>=1.86,<2.0
Requires-Dist: pandas>=2.3.3
Requires-Dist: slurmbench>=0.3.3
Requires-Python: >=3.13
Project-URL: Changelog, https://gitlab.com/vepain/plasmid_bin_bench-py/-/blob/main/CHANGELOG.md
Project-URL: Repository, https://gitlab.com/vepain/plasmid_bin_bench-py
